lossers/__init__.py
lossers/clip.py
lossers/gan.py
lossers/math.py
lossers/softmax.py
lossers/version.py
lossers-0.1.0.dist-info/LICENSE
lossers-0.1.0.dist-info/METADATA
lossers-0.1.0.dist-info/WHEEL
lossers-0.1.0.dist-info/top_level.txt
lossers-0.1.0.dist-info/RECORD
